statsnba/__init__.py
statsnba/api.py
statsnba/resources.py
statsnba/utils.py
statsnba_playbyplay-0.1.0.dist-info/DESCRIPTION.rst
statsnba_playbyplay-0.1.0.dist-info/METADATA
statsnba_playbyplay-0.1.0.dist-info/RECORD
statsnba_playbyplay-0.1.0.dist-info/WHEEL
statsnba_playbyplay-0.1.0.dist-info/metadata.json
statsnba_playbyplay-0.1.0.dist-info/pbr.json
statsnba_playbyplay-0.1.0.dist-info/top_level.txt
