Metadata-Version: 2.0
Name: statsnba-playbyplay
Version: 0.1.0
Summary: Package for parsing play-by-play data from stats.nba.com
Home-page: https://github.com/ethanluoyc/statsnba-playbyplay
Author: Yicheng Luo
Author-email: ethanluoyc@gmail.com
License: MIT
Keywords: statsnba
Platform: UNKNOWN
Requires-Dist: luigi
Requires-Dist: pandas
Requires-Dist: pymongo
Requires-Dist: requests
